[{"class_name": "0", "bbox": "0.111 0.351 0.022 0.087", "used": false}, {"class_name": "0", "bbox": "0.544 0.364 0.059 0.079", "used": false}, {"class_name": "0", "bbox": "0.381 0.199 0.087 0.099", "used": false}, {"class_name": "0", "bbox": "0.322 0.545 0.017 0.06", "used": false}, {"class_name": "0", "bbox": "0.078 0.36 0.032 0.058", "used": false}, {"class_name": "0", "bbox": "0.439 0.641 0.012 0.052", "used": false}, {"class_name": "0", "bbox": "0.498 0.686 0.007 0.047", "used": false}, {"class_name": "0", "bbox": "0.484 0.672 0.01 0.06", "used": false}, {"class_name": "0", "bbox": "0.465 0.664 0.015 0.05", "used": false}, {"class_name": "0", "bbox": "0.454 0.651 0.016 0.064", "used": false}, {"class_name": "0", "bbox": "0.301 0.523 0.01 0.056", "used": false}, {"class_name": "0", "bbox": "0.157 0.385 0.025 0.081", "used": false}, {"class_name": "0", "bbox": "0.274 0.505 0.013 0.046", "used": false}, {"class_name": "0", "bbox": "0.454 0.359 0.908 0.695", "used": false}]