[{"class_name": "1", "bbox": "0.299 0.726 0.288 0.475", "used": false}, {"class_name": "1", "bbox": "0.562 0.785 0.209 0.344", "used": false}, {"class_name": "0", "bbox": "0.439 0.556 0.21 0.726", "used": false}, {"class_name": "0", "bbox": "0.677 0.417 0.06 0.235", "used": false}, {"class_name": "0", "bbox": "0.766 0.529 0.159 0.458", "used": false}, {"class_name": "0", "bbox": "0.561 0.539 0.148 0.607", "used": false}, {"class_name": "0", "bbox": "0.957 0.462 0.086 0.276", "used": false}, {"class_name": "0", "bbox": "0.633 0.228 0.042 0.17", "used": false}]